geocities/__init__.py
geocities/geocities.py
geocities-0.0.1.dist-info/LICENSE
geocities-0.0.1.dist-info/METADATA
geocities-0.0.1.dist-info/WHEEL
geocities-0.0.1.dist-info/top_level.txt
geocities-0.0.1.dist-info/RECORD
